vedro_logs_checker/__init__.py
vedro_logs_checker/vedro_logs_checker.py
vedro_logs_checker-0.0.9.dist-info/METADATA
vedro_logs_checker-0.0.9.dist-info/WHEEL
vedro_logs_checker-0.0.9.dist-info/top_level.txt
vedro_logs_checker-0.0.9.dist-info/RECORD
