Metadata-Version: 2.4
Name: vedro-logs-checker
Version: 0.0.9
Summary: vedro-logs-checker for the vedro.io framework
Home-page: https://github.com/GeneralKenobiego/vedro-logs-checker
Author: Denis Tokarev
Author-email: ggki4p@proton.me
License: Apache-2.0
Classifier: License :: OSI Approved :: Apache Software License
Classifier: Programming Language :: Python :: 3.10
Classifier: Programming Language :: Python :: 3.11
Requires-Python: >=3.10
Requires-Dist: vedro<2.0,>=1.10.0
Requires-Dist: docker>=5.0.3
Dynamic: author
Dynamic: author-email
Dynamic: classifier
Dynamic: description
Dynamic: description-content-type
Dynamic: home-page
Dynamic: license
Dynamic: requires-dist
Dynamic: requires-python
Dynamic: summary
